pact/__init__.py
pact/__version__.py
pact/__version__.pyi
pact/_server.py
pact/_util.py
pact/error.py
pact/pact.py
pact/py.typed
pact/types.py
pact/types.pyi
pact/verifier.py
pact/generate/__init__.py
pact/generate/generator.py
pact/interaction/__init__.py
pact/interaction/_async_message_interaction.py
pact/interaction/_base.py
pact/interaction/_http_interaction.py
pact/interaction/_sync_message_interaction.py
pact/match/__init__.py
pact/match/matcher.py
pact/v2/__init__.py
pact/v2/broker.py
pact/v2/constants.py
pact/v2/consumer.py
pact/v2/http_proxy.py
pact/v2/matchers.py
pact/v2/message_consumer.py
pact/v2/message_pact.py
pact/v2/message_provider.py
pact/v2/pact.py
pact/v2/provider.py
pact/v2/verifier.py
pact/v2/verify_wrapper.py
pact/v2/cli/__init__.py
pact/v2/cli/verify.py
pact_python-3.1.0.dist-info/METADATA
pact_python-3.1.0.dist-info/WHEEL
pact_python-3.1.0.dist-info/entry_points.txt
pact_python-3.1.0.dist-info/licenses/LICENSE
pact_python-3.1.0.dist-info/RECORD
