Metadata-Version: 2.4
Name: pact-python
Version: 3.1.0
Summary: Tool for creating and verifying consumer-driven contracts using the Pact framework.
Project-URL: changelog, https://github.com/pact-foundation/pact-python/blob/main/CHANGELOG.md
Project-URL: documentation, https://pact-foundation.github.io/pact-python/
Project-URL: homepage, https://pact.io
Project-URL: issues, https://github.com/pact-foundation/pact-python/issues
Project-URL: source, https://github.com/pact-foundation/pact-python
Author-email: Joshua Ellis <josh@jpellis.me>, Matthew Balvanz <matthew.balvanz@workiva.com>
Maintainer-email: Joshua Ellis <josh@jpellis.me>
License: MIT License
License-File: LICENSE
Keywords: contract-testing,pact,testing
Classifier: Development Status :: 5 - Production/Stable
Classifier: Environment :: Console
Classifier: Intended Audience :: Developers
Classifier: License :: OSI Approved :: MIT License
Classifier: Operating System :: MacOS :: MacOS X
Classifier: Operating System :: Microsoft :: Windows
Classifier: Operating System :: POSIX :: Linux
Classifier: Programming Language :: Python
Classifier: Programming Language :: Python :: 3 :: Only
Classifier: Programming Language :: Python :: 3.10
Classifier: Programming Language :: Python :: 3.11
Classifier: Programming Language :: Python :: 3.12
Classifier: Programming Language :: Python :: 3.13
Classifier: Programming Language :: Python :: 3.14
Classifier: Topic :: Software Development :: Testing
Requires-Python: >=3.10
Requires-Dist: pact-python-ffi~=0.4.0
Requires-Dist: yarl~=1.0
Provides-Extra: compat-v2
Requires-Dist: click~=8.0; extra == 'compat-v2'
Requires-Dist: pact-python-cli~=2.0; extra == 'compat-v2'
Requires-Dist: psutil~=7.0; extra == 'compat-v2'
Requires-Dist: requests~=2.0; extra == 'compat-v2'
Requires-Dist: six~=1.0; extra == 'compat-v2'
